odoo/addons/l10n_th_expense_tax_invoice/README.rst
odoo/addons/l10n_th_expense_tax_invoice/__init__.py
odoo/addons/l10n_th_expense_tax_invoice/__manifest__.py
odoo/addons/l10n_th_expense_tax_invoice/i18n/l10n_th_expense_tax_invoice.pot
odoo/addons/l10n_th_expense_tax_invoice/i18n/th.po
odoo/addons/l10n_th_expense_tax_invoice/models/__init__.py
odoo/addons/l10n_th_expense_tax_invoice/models/account_move.py
odoo/addons/l10n_th_expense_tax_invoice/models/hr_expense.py
odoo/addons/l10n_th_expense_tax_invoice/readme/CONTRIBUTORS.rst
odoo/addons/l10n_th_expense_tax_invoice/readme/DESCRIPTION.rst
odoo/addons/l10n_th_expense_tax_invoice/static/description/icon.png
odoo/addons/l10n_th_expense_tax_invoice/static/description/index.html
odoo/addons/l10n_th_expense_tax_invoice/tests/__init__.py
odoo/addons/l10n_th_expense_tax_invoice/tests/test_expense_tax_invoice.py
odoo/addons/l10n_th_expense_tax_invoice/views/hr_expense_view.xml
odoo13_addon_l10n_th_expense_tax_invoice-13.0.1.0.1.dev6.dist-info/METADATA
odoo13_addon_l10n_th_expense_tax_invoice-13.0.1.0.1.dev6.dist-info/WHEEL
odoo13_addon_l10n_th_expense_tax_invoice-13.0.1.0.1.dev6.dist-info/top_level.txt
odoo13_addon_l10n_th_expense_tax_invoice-13.0.1.0.1.dev6.dist-info/RECORD
